cargo/__init__.py
cargo/api.py
vitddnv-0.0.2.dist-info/LICENSE
vitddnv-0.0.2.dist-info/METADATA
vitddnv-0.0.2.dist-info/WHEEL
vitddnv-0.0.2.dist-info/top_level.txt
vitddnv-0.0.2.dist-info/RECORD
