Metadata-Version: 2.1
Name: vitddnv
Version: 0.0.2
Summary: Vhinny Financial Data API
Home-page: https://github.com/vhinny-investing/api
Author: Vitalii Dodonov
Author-email: admin@vhinny.com
License: UNKNOWN
Platform: UNKNOWN
Classifier: Programming Language :: Python :: 3
Classifier: License :: OSI Approved :: MIT License
Classifier: Operating System :: OS Independent
Requires-Python: >=3.6
